grub2_theme_preview/__init__.py
grub2_theme_preview/__main__.py
grub2_theme_preview/version.py
grub2_theme_preview/which.py
grub2_theme_preview/tests/__init__.py
grub2_theme_preview/tests/test_main.py
grub2_theme_preview-2.9.0.dist-info/METADATA
grub2_theme_preview-2.9.0.dist-info/WHEEL
grub2_theme_preview-2.9.0.dist-info/entry_points.txt
grub2_theme_preview-2.9.0.dist-info/top_level.txt
grub2_theme_preview-2.9.0.dist-info/RECORD
